codecheck/__init__.py
codecheck/checker_copyright_year.py
codecheck/checker_cyclic_import.py
codecheck/checker_dependencies.py
codecheck/checker_jupyter.py
codecheck/checker_mypy_annotations.py
codecheck/checker_py_headers.py
codecheck/checker_pydocstyle.py
codecheck/default_cfg.yaml
codecheck/gitcov.py
codecheck/main.py
codecheck/task_scheduler.py
nxp_codecheck-0.3.16.dist-info/licenses/LICENSE
nxp_codecheck-0.3.16.dist-info/METADATA
nxp_codecheck-0.3.16.dist-info/WHEEL
nxp_codecheck-0.3.16.dist-info/entry_points.txt
nxp_codecheck-0.3.16.dist-info/top_level.txt
nxp_codecheck-0.3.16.dist-info/RECORD
